usefuladb/README.MD
usefuladb/__init__.py
usefuladb/c.py
usefuladb/keyevents.py
usefuladb/parsekeyevents.py
usefuladb/requirements.txt
usefuladb/thirdparty.json
usefuladb-0.25.dist-info/LICENSE.rst
usefuladb-0.25.dist-info/METADATA
usefuladb-0.25.dist-info/WHEEL
usefuladb-0.25.dist-info/top_level.txt
usefuladb-0.25.dist-info/RECORD
