Metadata-Version: 2.1
Name: usefuladb
Version: 0.25
Summary: A collection of useful adb commands
Home-page: https://github.com/hansalemaos/usefuladb
Author: Johannes Fischer
Author-email: aulasparticularesdealemaosp@gmail.com
License: MIT
Keywords: adb,android
Classifier: Development Status :: 4 - Beta
Classifier: Programming Language :: Python :: 3 :: Only
Classifier: Programming Language :: Python :: 3.10
Classifier: Topic :: Software Development :: Libraries :: Python Modules
Classifier: Topic :: Utilities
License-File: LICENSE.rst
Requires-Dist: argskwargsmodifierclass
Requires-Dist: fabisschomagut
Requires-Dist: flatten-any-dict-iterable-or-whatsoever
Requires-Dist: flatten-everything
Requires-Dist: indent2dict
Requires-Dist: lxml
Requires-Dist: nclib
Requires-Dist: normaltext
Requires-Dist: parifinder
Requires-Dist: punktdict
Requires-Dist: requests
Requires-Dist: touchtouch
